setup.cfg
setup.py
secureheaderscanner/__init__.py
secureheaderscanner/scan.py
secureheaderscanner.egg-info/PKG-INFO
secureheaderscanner.egg-info/SOURCES.txt
secureheaderscanner.egg-info/dependency_links.txt
secureheaderscanner.egg-info/not-zip-safe
secureheaderscanner.egg-info/top_level.txt