Metadata-Version: 1.0
Name: secureheaderscanner
Version: 0.5
Summary: Scan URLs for presence of secure HTTP headers
Home-page: http://github.com/gaurabb/secureheaderscanner
Author: Gaurab B
Author-email: gaurabb@hotmail.com
License: MIT
Platform: UNKNOWN
